deployhub/__init__.py
deployhub/dhapi.py
ortelius_cli-9.3.281.data/scripts/dh
ortelius_cli-9.3.281.dist-info/licenses/LICENSE
ortelius_cli-9.3.281.dist-info/METADATA
ortelius_cli-9.3.281.dist-info/WHEEL
ortelius_cli-9.3.281.dist-info/top_level.txt
ortelius_cli-9.3.281.dist-info/RECORD
