Metadata-Version: 2.4
Name: ortelius-cli
Version: 9.3.281
Home-page: https://ortelius.io
Author: Steve Taylor
Author-email: steve@deployhub.com
License: Apache-2.0
Project-URL: Project Repo, https://github.com/ortelius/ortelius-cli
Project-URL: Issues, https://github.com/ortelius/ortelius/issues
Project-URL: Ortelius CLI Documentation, https://github.com/ortelius/ortelius-cli/blob/main/doc/dh.md
Project-URL: Python Python API Documentation, https://github.com/ortelius/ortelius-cli/blob/main/doc/deployhub.md
Requires-Python: >=3.6
License-File: LICENSE
Requires-Dist: click
Requires-Dist: qtoml
Requires-Dist: pyyaml
Requires-Dist: requests
Requires-Dist: configobj
Requires-Dist: flatten_dict
Requires-Dist: pydantic
Requires-Dist: certifi
Dynamic: author
Dynamic: author-email
Dynamic: description
Dynamic: description-content-type
Dynamic: home-page
Dynamic: license
Dynamic: license-file
Dynamic: project-url
Dynamic: requires-dist
Dynamic: requires-python
